gamma/__init__.py
gamma/game.py
gamma/gamma.py
gamma/globals.py
gamma/components/component_battle.py
gamma/components/component_camera.py
gamma/components/component_collider.py
gamma/components/component_crafting.py
gamma/components/component_emote.py
gamma/components/component_input.py
gamma/components/component_inventory.py
gamma/components/component_motion.py
gamma/components/component_particle_emitter.py
gamma/components/component_position.py
gamma/components/component_sprites.py
gamma/components/component_tags.py
gamma/components/component_text.py
gamma/components/component_trauma.py
gamma/components/component_triggers.py
gamma/core/assets.py
gamma/core/colours.py
gamma/core/component.py
gamma/core/crafting_recipe.py
gamma/core/cutscene.py
gamma/core/entity.py
gamma/core/entity_factory.py
gamma/core/hitbox.py
gamma/core/hurtbox.py
gamma/core/map.py
gamma/core/particle.py
gamma/core/renderable.py
gamma/core/renderer.py
gamma/core/scene.py
gamma/core/sprite.py
gamma/core/system.py
gamma/core/tile.py
gamma/core/transition.py
gamma/fonts/munro.ttf
gamma/images/emote_box.png
gamma/images/gamma.png
gamma/images/tile_outline.png
gamma/input/controller.py
gamma/input/keyboard.py
gamma/managers/manager_entity.py
gamma/managers/manager_input.py
gamma/managers/manager_scene.py
gamma/managers/manager_sound.py
gamma/managers/manager_system.py
gamma/managers/manager_tile.py
gamma/renderables/circle.py
gamma/renderables/image.py
gamma/renderables/rectangle.py
gamma/renderables/text.py
gamma/systems/system_animation.py
gamma/systems/system_battle.py
gamma/systems/system_camera.py
gamma/systems/system_collision.py
gamma/systems/system_crafting.py
gamma/systems/system_emote.py
gamma/systems/system_image.py
gamma/systems/system_input.py
gamma/systems/system_inventory.py
gamma/systems/system_particle.py
gamma/systems/system_physics.py
gamma/systems/system_text.py
gamma/systems/system_trauma.py
gamma/systems/system_trigger.py
gamma/transitions/transition_black.py
pygame_gamma-0.5.dist-info/METADATA
pygame_gamma-0.5.dist-info/WHEEL
pygame_gamma-0.5.dist-info/licenses/LICENSE
pygame_gamma-0.5.dist-info/RECORD
