Metadata-Version: 2.3
Name: pygame-gamma
Version: 0.5
Summary: A simple ECS game engine for Python, built on Pygame, with an emphasis on ease of use
Project-URL: Homepage, https://github.com/rik-cross/gamma
Project-URL: Suggestions and bugs, https://github.com/rik-cross/gamma/issues
Author-email: Rik Cross <rik.j.cross@gmail.com>
License-File: LICENSE
Classifier: License :: OSI Approved :: MIT License
Classifier: Operating System :: OS Independent
Classifier: Programming Language :: Python :: 3
Requires-Python: >=3.7
